fileutility/__init__.py
fileutility/fileutility.py
fileutility-0.6.dist-info/LICENSE
fileutility-0.6.dist-info/METADATA
fileutility-0.6.dist-info/WHEEL
fileutility-0.6.dist-info/top_level.txt
fileutility-0.6.dist-info/RECORD
