Metadata-Version: 2.1
Name: fileutility
Version: 0.6
Summary: Helper module for locating and deleting files and folders.
Home-page: https://github.com/Pixxle/fileutility
Author: Dennis Hedlund
Author-email: dennishedlund@gmail.com
License: UNKNOWN
Platform: UNKNOWN
Classifier: Programming Language :: Python :: 2
Classifier: License :: OSI Approved :: MIT License
Classifier: Operating System :: OS Independent
